pyvarstr/__init__.py
pyvarstr/main.py
pyvarstr-0.0.12.dist-info/METADATA
pyvarstr-0.0.12.dist-info/WHEEL
pyvarstr-0.0.12.dist-info/licenses/LICENSE
pyvarstr-0.0.12.dist-info/RECORD
