Metadata-Version: 2.4
Name: pyvarstr
Version: 0.0.12
Summary: This library is in initial stage of development.
Author-email: sdelta199 <sdelta199@yandex.ru>
License-File: LICENSE
Classifier: License :: OSI Approved :: MIT License
Classifier: Operating System :: OS Independent
Classifier: Programming Language :: Python :: 3
Requires-Python: >=3.6.0
